gridder/__init__.py
gridder/constants.py
gridder/converter.py
gridder/drawer.py
gridder/gridder.py
gridder/main.py
gridder-1.1.0.dist-info/LICENSE.txt
gridder-1.1.0.dist-info/METADATA
gridder-1.1.0.dist-info/WHEEL
gridder-1.1.0.dist-info/top_level.txt
gridder-1.1.0.dist-info/RECORD
