Metadata-Version: 2.1
Name: gridder
Version: 1.1.0
Summary: Generate tiles and grids over images.
Home-page: https://gitlab.com/brzrkr/gridder
Author: Federico Salerno
Author-email: itashadd+gridder@gmail.com
License: UNKNOWN
Project-URL: Source, https://gitlab.com/brzrkr/gridder
Keywords: grid tile tileset image generator
Platform: UNKNOWN
Classifier: Development Status :: 5 - Production/Stable
Classifier: Environment :: Console
Classifier: Intended Audience :: End Users/Desktop
Classifier: License :: OSI Approved :: GNU General Public License v3 or later (GPLv3+)
Classifier: Natural Language :: English
Classifier: Programming Language :: Python :: 3
Classifier: Programming Language :: Python :: 3.2
Classifier: Programming Language :: Python :: 3.3
Classifier: Programming Language :: Python :: 3.4
Classifier: Programming Language :: Python :: 3.5
Classifier: Programming Language :: Python :: 3.6
Classifier: Topic :: Multimedia :: Graphics
Classifier: Topic :: Utilities
Requires-Python: >=3.2
Requires-Dist: Pillow
Requires-Dist: numpy
